TracHTTPAuth-1.2.dist-info/DESCRIPTION.rst
TracHTTPAuth-1.2.dist-info/METADATA
TracHTTPAuth-1.2.dist-info/RECORD
TracHTTPAuth-1.2.dist-info/WHEEL
TracHTTPAuth-1.2.dist-info/entry_points.txt
TracHTTPAuth-1.2.dist-info/metadata.json
TracHTTPAuth-1.2.dist-info/top_level.txt
httpauth/__init__.py
httpauth/filter.py
